atarihns/__init__.py
atarihns/constants.py
atarihns/helpers.py
atarihns-0.0.17.dist-info/licenses/LICENSE
atarihns-0.0.17.dist-info/METADATA
atarihns-0.0.17.dist-info/WHEEL
atarihns-0.0.17.dist-info/top_level.txt
atarihns-0.0.17.dist-info/RECORD
