Metadata-Version: 2.4
Name: atarihns
Version: 0.0.17
Summary: A little helper to calculate human normalized score for different ALE environments efficiently.
Author-email: Taha Shieenavaz <tahashieenavaz@gmail.com>
License: MIT License
Project-URL: Homepage, https://github.com/tahashieenavaz/atarihns
Project-URL: Repository, https://github.com/tahashieenavaz/atarihns
Project-URL: Documentation, https://github.com/tahashieenavaz/atarihns#readme
Keywords: reinforcement learning,atari,human normalized score,hns score
Classifier: Programming Language :: Python :: 3
Classifier: License :: OSI Approved :: MIT License
Classifier: Operating System :: OS Independent
Classifier: Development Status :: 4 - Beta
Classifier: Intended Audience :: Developers
Classifier: Topic :: Software Development :: Libraries :: Python Modules
Requires-Python: >=3.9
License-File: LICENSE
Dynamic: license-file
